tests/__init__.py
tests/test_vod_metadata.py
vod_metadata/__init__.py
vod_metadata/__main__.py
vod_metadata/config_read.py
vod_metadata/md5_calc.py
vod_metadata/md_gen.py
vod_metadata/media_info.py
vod_metadata/metadata_template.xml
vod_metadata/utils.py
vod_metadata/vod_config.ini
vod_metadata/vodpackage.py
vod_metadata/xml_helper.py
vod_metadata-2016.1.6.dist-info/DESCRIPTION.rst
vod_metadata-2016.1.6.dist-info/METADATA
vod_metadata-2016.1.6.dist-info/RECORD
vod_metadata-2016.1.6.dist-info/WHEEL
vod_metadata-2016.1.6.dist-info/metadata.json
vod_metadata-2016.1.6.dist-info/top_level.txt
