Metadata-Version: 2.0
Name: vod-metadata
Version: 2016.1.6
Summary: CableLabs VOD Metadata 1.1 library and tools
Home-page: https://github.com/bbayles/vod_metadata
Author: Bo Bayles
Author-email: bbayles@gmail.com
License: MIT
Keywords: cablelabs vod metadata
Platform: UNKNOWN
Classifier: Development Status :: 5 - Production/Stable
Classifier: Intended Audience :: Telecommunications Industry
Classifier: Topic :: Utilities
Classifier: License :: OSI Approved :: MIT License
Classifier: Programming Language :: Python :: 2.7
Classifier: Programming Language :: Python :: 3
